globus_nexus_client/__init__.py
globus_nexus_client/py.typed
globus_nexus_client-0.4.1.dist-info/COPYING
globus_nexus_client-0.4.1.dist-info/LICENSE
globus_nexus_client-0.4.1.dist-info/METADATA
globus_nexus_client-0.4.1.dist-info/WHEEL
globus_nexus_client-0.4.1.dist-info/top_level.txt
globus_nexus_client-0.4.1.dist-info/RECORD
