Metadata-Version: 2.1
Name: globus-nexus-client
Version: 0.4.1
Summary: Unofficial Globus Nexus Client (based on SDK clients)
Home-page: https://github.com/sirosen/globus-nexus-client
Author: Stephen Rosen
Author-email: sirosen@globus.org
License: UNKNOWN
Platform: UNKNOWN
Classifier: Development Status :: 4 - Beta
Classifier: Intended Audience :: Developers
Classifier: License :: OSI Approved :: Apache Software License
Classifier: Programming Language :: Python :: 3
Requires-Python: >=3.6.2
License-File: LICENSE
License-File: COPYING
Requires-Dist: globus-sdk (<4,>=3.0.0)
